{
	"type" : "FeatureCollection",
	"name" : "QFESWarnings",
	"features" : [
		{
			"type" : "Feature",
			"geometry" : {
				"type" : "Polygon",
				"coordinates" : [
					[
						[ 152.0312053585, -28.2492758835, 0 ],
						[ 152.0306903744, -28.2515440986, 0 ],
						[ 152.0459038639, -28.2522056522, 0 ],
						[ 152.0485646153, -28.2449283365, 0 ],
						[ 152.0416123295, -28.241336751, 0 ],
						[ 152.0333511257, -28.2402403481, 0 ],
						[ 152.0312053585, -28.2492758835, 0 ]
					]
				]
			},
			"properties" : {
				"OBJECTID" : "4321",
				"UniqueID" : "IF39-3625721",
				"WarningTitle" : "STAY INFORMED - Morgan Park (near Warwick) - fire as at  6:02pm Friday, 30 August 2024",
				"WarningLevel" : "Advice",
				"CallToAction" : "STAY INFORMED",
				"WarningText" : "\nSTAY INFORMED - Morgan Park (near Warwick) - fire as at  6:02pm Friday, 30 August 2024 \n\n \n\n\nWarning level: ADVICE\n\n\n \n\n\nWarning area: between Warwick Killarney Road, Old Stanthorpe Road and Kenilworth Street \n\n\n \n\nA fire is burning along Old Stanthorpe Road. It is moving towards Warwick Killarney Road. ‎\n\n \n\n‎ Major roads or highways may be impacted, including Old Stanthorpe Road, near Morgan Park.\n\n\n \n\nWhat you should do:\n\n- Stay informed because conditions could change:\n\n- Check the QFD Current Bushfires and Warnings website regularly.\n\n- Follow QFD on Facebook and X.com.\n\n- Listen to your local radio station.\n\n- Tell friends, family and neighbours in the area.\n\n- Decide what you will do if the bushfire gets closer.\n\n- Follow your bushfire survival plan now. If you do not have a bushfire survival plan, make one on the QFD website.\n\n- Decide where you and the people you live with will go. This could be with family or a friend away from the fire.\n\n- Keep medications close by.\n\n- Avoid smoke – stay indoors, close windows and doors, and avoid driving through smoke.\n\n- Watch out for firefighters working in the area.\n\n- Do not fly drones around the fire. Drones affect air operations.\n\n- If your life is in danger, call Triple Zero (000) immediately.\n\n\n\n \n\nImpacts:\n\n- No properties are at risk.\n\n- Smoke can make it hard for some people to breathe.\n\n- Smoke can make it hard to see when you are driving.\n\n- Some roads may be closed.\n\n\n\n \n\nFurther Information:\n\n- For all warnings, visit the QFD Current Bushfires and Warnings website.\n\n- Follow QFD on Facebook and X.com.\n\n- For road closures, visit the QLD Traffic website or call 13 19 40.\n\n- Visit the Department of Environment and Science website for live air quality data.\n\n- Find out how to get ready for a bushfire on the QFD website under Prepare - Bushfire.\n\n\n\n \n\nUpdates will be issued as the situation changes.\n\n \n\nThis warning is from Queensland Fire Department.\n\n",
				"Header" : "A fire is burning along Old Stanthorpe Road. It is moving towards Warwick Killarney Road. ‎\r\n\r\n‎ Major roads or highways may be impacted, including Old Stanthorpe Road, near Morgan Park .",
				"Impacts" : "- No properties are at risk.\r\n\r\n- Smoke can make it hard for some people to breathe.\r\n\r\n- Smoke can make it hard to see when you are driving.\r\n\r\n- Some roads may be closed.",
				"LeaveSafely" : null,
				"FurtherInformation" : "- For all warnings, visit the QFD Current Bushfires and Warnings website.\n\n- Follow QFD on Facebook and X.com.\n\n- For road closures, visit the QLD Traffic website or call 13 19 40.\n\n- Visit the Department of Environment and Science website for live air quality data.\n\n- Find out how to get ready for a bushfire on the QFD website under Prepare - Bushfire.\r\n\r\n\r\nUpdates will be issued as the situation changes.\r\n\r\nThis warning is from Queensland Fire Department.",
				"WarningLevelSort" : "5",
				"ShouldDo" : "- Stay informed because conditions could change:\r\n\r\n- Check the QFD Current Bushfires and Warnings website regularly.\r\n\r\n- Follow QFD on Facebook and X.com.\r\n\r\n- Listen to your local radio station.\r\n\r\n- Tell friends, family and neighbours in the area.\r\n\r\n- Decide what you will do if the bushfire gets closer:\r\n\r\n- Follow your bushfire survival plan now. If you do not have a bushfire survival plan, make one on the QFD website.\r\n\r\n- Decide where you and the people you live with will go. This could be with family or a friend away from the fire.\r\n\r\n- Keep medications close by.\r\n\r\n- Avoid smoke - stay indoors, close windows and doors, and avoid driving through smoke.\r\n\r\n- Watch out for firefighters working in the area.\r\n\r\n- Do not fly drones around the fire. Drones affect air operations.\r\n\r\n- If your life is in danger, call Triple Zero (000) immediately.",
				"WarningArea" : "between Warwick Killarney Road, Old Stanthorpe Road and Kenilworth Street",
				"Master_Incident_Number" : "QF3-24-104817",
				"CurrentStatus" : "Patrolled",
				"Location" : "Old Stanthorpe Rd",
				"Jurisdiction" : "3 South Western Region",
				"Latitude" : -28.246610669205,
				"Longitude" : 152.03938073161,
				"VehiclesAssigned" : "0",
				"VehiclesOnRoute" : "0",
				"VehiclesOnScene" : "0",
				"GroupedType" : "FIRE VEGETATION",
				"Locality" : "MORGAN PARK",
				"ItemDateTimeUTM" : "20240830080100",
				"ItemDateTimeLocal_ISO" : "2024-08-30T18:01:00+10:00",
				"PublishDateLocal_ISO" : "2024-08-30T23:46:07+10:00",
				"ItemExpiryDateTimeLocal_ISO" : "2024-08-31T18:01:00+10:00"
			}
		},
		{
			"type" : "Feature",
			"geometry" : {
				"type" : "Polygon",
				"coordinates" : [
					[
						[ 152.5410812822, -26.8777511421, 0 ],
						[ 152.5409096208, -26.9646883107, 0 ],
						[ 152.6456230608, -26.9741738745, 0 ],
						[ 152.6703422991, -26.9013287526, 0 ],
						[ 152.6116341082, -26.8890812573, 0 ],
						[ 152.5410812822, -26.8777511421, 0 ]
					]
				]
			},
			"properties" : {
				"OBJECTID" : "4307",
				"UniqueID" : "IF39-3622621",
				"WarningTitle" : "AVOID SMOKE - Kilcoy - fire as at  3:32pm Thursday, 29 August 2024",
				"WarningLevel" : "Advice",
				"CallToAction" : "AVOID SMOKE",
				"WarningText" : "\nAVOID SMOKE - Kilcoy - fire as at  3:32pm Thursday, 29 August 2024 \n\n \n\nWarning level: ADVICE\n\n \n\n\nWarning area: Kilcoy, Sandy Creek, Glenfern and surrounding areas\n\n\n \n\nSmoke is currently affecting Kilcoy, Sandy Creek, Glenfern and surrounding areas. This is from a fire burning near Mount Kilcoy Road.\n\n\n \n\nWhat you should do:\n\n- Stay inside and close windows and doors.\n\n- Keep respiratory medication close by.\n\n- Follow your bushfire survival plan now. If you do not have a bushfire survival plan, make one on the QFD website.\n\n- Avoid driving through smoke if you can.\n\n- Watch out for firefighters working in the area.\n\n- Do not fly drones around the fire. Drones affect air operations.\n\n\n\n \n\nImpacts:\n\n- No properties are at risk.\n\n- Smoke can make it hard for some people to breathe.\n\n- Smoke can make it hard to see when you are driving.\n\n- Some roads may be closed.\n\n\n\n \n\nFurther Information:\n\n- For all warnings, visit the QFD Current Bushfires and Warnings website.\n\n- Follow QFD on Facebook and X.com.\n\n- For road closures, visit the QLD Traffic website or call 13 19 40.\n\n- Visit the Department of Environment and Science website for live air quality data.\n\n- Find out how to get ready for a bushfire on the QFD website under Prepare - Bushfire.\n\n\n\n \n\nUpdates will be issued if the situation changes.\n\n \n\nThis warning is from Queensland Fire Department.\n\n",
				"Header" : "Smoke is currently affecting Kilcoy, Sandy Creek, Glenfern and surrounding areas. This is from a fire burning near Mount Kilcoy Road.",
				"Impacts" : "- No properties are at risk.\r\n\r\n- Smoke can make it hard for some people to breathe.\r\n\r\n- Smoke can make it hard to see when you are driving.\r\n\r\n- Some roads may be closed.",
				"LeaveSafely" : null,
				"FurtherInformation" : "- For all warnings, visit the QFD Current Bushfires and Warnings website.\n\n- Follow QFD on Facebook and X.com.\n\n- For road closures, visit the QLD Traffic website or call 13 19 40.\n\n- Visit the Department of Environment and Science website for live air quality data.\n\n- Find out how to get ready for a bushfire on the QFD website under Prepare - Bushfire.\r\n\r\n\r\nUpdates will be issued if the situation changes.\r\n\r\nThis warning is from Queensland Fire Department.",
				"WarningLevelSort" : "7",
				"ShouldDo" : "- Stay inside and close windows and doors.\r\n\r\n- Keep respiratory medication close by.\r\n\r\n- Follow your bushfire survival plan now. If you do not have a bushfire survival plan, make one on the QFD website.\r\n\r\n- Avoid driving through smoke if you can.\r\n\r\n- Watch out for firefighters working in the area.\r\n\r\n- Do not fly drones around the fire. Drones affect air operations.",
				"WarningArea" : "Kilcoy, Sandy Creek, Glenfern and surrounding areas",
				"Latitude" : -26.932247766549,
				"Longitude" : 152.59685513648,
				"GroupedType" : "FIRE VEGETATION",
				"ItemDateTimeUTM" : "20240829052900",
				"ItemDateTimeLocal_ISO" : "2024-08-29T15:29:00+10:00",
				"PublishDateLocal_ISO" : "2024-08-30T23:46:08+10:00",
				"ItemExpiryDateTimeLocal_ISO" : "2024-08-30T15:29:00+10:00"
			}
		},
		{
			"type" : "Feature",
			"geometry" : {
				"type" : "Polygon",
				"coordinates" : [
					[
						[ 152.8000930199, -27.820268487, 0 ],
						[ 152.7987197288, -27.9122324341, 0 ],
						[ 152.9872039207, -27.9680404103, 0 ],
						[ 153.0689147362, -27.8396997151, 0 ],
						[ 152.904463137, -27.7747129206, 0 ],
						[ 152.8000930199, -27.820268487, 0 ]
					]
				]
			},
			"properties" : {
				"OBJECTID" : "4318",
				"UniqueID" : "IF39-3624521",
				"WarningTitle" : "AVOID SMOKE - Kagaru (near Jimboomba) - fire as at  3:22pm Friday, 30 August 2024",
				"WarningLevel" : "Advice",
				"CallToAction" : "AVOID SMOKE",
				"WarningText" : "\nAVOID SMOKE - Kagaru (near Jimboomba) - fire as at  3:22pm Friday, 30 August 2024 \n\n \n\nWarning level: ADVICE\n\n \n\n\nWarning area: Kagaru, Cedar Grove, Gleneagle, Veresdale Scrub and surrounding areas\n\n\n \n\nSmoke is currently affecting Kagaru, Cedar Grove, Gleneagle, Veresdale Scrub and surrounding areas. This is from a fire burning near Undullah Road and Brookland Road, Kagaru.\n\n\n \n\nWhat you should do:\n\n- Stay inside and close windows and doors.\n\n- Keep respiratory medication close by.\n\n- Follow your bushfire survival plan now. If you do not have a bushfire survival plan, make one on the QFD website.\n\n- Avoid driving through smoke if you can.\n\n- Watch out for firefighters working in the area.\n\n- Do not fly drones around the fire. Drones affect air operations.\n\n\n\n \n\nImpacts:\n\n- No properties are at risk.\n\n- Smoke can make it hard for some people to breathe.\n\n- Smoke can make it hard to see when you are driving.\n\n- Some roads may be closed.\n\n\n\n \n\nFurther Information:\n\n- For all warnings, visit the QFD Current Bushfires and Warnings website.\n\n- Follow QFD on Facebook and X.com.\n\n- For road closures, visit the QLD Traffic website or call 13 19 40.\n\n- Visit the Department of Environment and Science website for live air quality data.\n\n- Find out how to get ready for a bushfire on the QFD website under Prepare - Bushfire.\n\n\n\n \n\nUpdates will be issued if the situation changes.\n\n \n\nThis warning is from Queensland Fire Department.\n\n",
				"Header" : "Smoke is currently affecting Kagaru, Cedar Grove, Gleneagle, Veresdale Scrub and surrounding areas. This is from a fire burning near Undullah Road and Brookland Road, Kagaru.",
				"Impacts" : "- No properties are at risk.\r\n\r\n- Smoke can make it hard for some people to breathe.\r\n\r\n- Smoke can make it hard to see when you are driving.\r\n\r\n- Some roads may be closed.",
				"LeaveSafely" : null,
				"FurtherInformation" : "- For all warnings, visit the QFD Current Bushfires and Warnings website.\n\n- Follow QFD on Facebook and X.com.\n\n- For road closures, visit the QLD Traffic website or call 13 19 40.\n\n- Visit the Department of Environment and Science website for live air quality data.\n\n- Find out how to get ready for a bushfire on the QFD website under Prepare - Bushfire.\r\n\r\n\r\nUpdates will be issued if the situation changes.\r\n\r\nThis warning is from Queensland Fire Department.",
				"WarningLevelSort" : "7",
				"ShouldDo" : "- Stay inside and close windows and doors.\r\n\r\n- Keep respiratory medication close by.\r\n\r\n- Follow your bushfire survival plan now. If you do not have a bushfire survival plan, make one on the QFD website.\r\n\r\n- Avoid driving through smoke if you can.\r\n\r\n- Watch out for firefighters working in the area.\r\n\r\n- Do not fly drones around the fire. Drones affect air operations.",
				"WarningArea" : "Kagaru, Cedar Grove, Gleneagle, Veresdale Scrub and surrounding areas",
				"Latitude" : -27.864894406107,
				"Longitude" : 152.93192895735,
				"GroupedType" : "FIRE VEGETATION",
				"ItemDateTimeUTM" : "20240830052100",
				"ItemDateTimeLocal_ISO" : "2024-08-30T15:21:00+10:00",
				"PublishDateLocal_ISO" : "2024-08-30T23:46:08+10:00",
				"ItemExpiryDateTimeLocal_ISO" : "2024-08-31T15:21:00+10:00"
			}
		},
		{
			"type" : "Feature",
			"geometry" : {
				"type" : "Polygon",
				"coordinates" : [
					[
						[ 152.2566128073, -28.2558628398, 0 ],
						[ 152.2847652731, -28.3664885658, 0 ],
						[ 152.4389171896, -28.3120968501, 0 ],
						[ 152.3874187766, -28.2192645638, 0 ],
						[ 152.2566128073, -28.2558628398, 0 ]
					]
				]
			},
			"properties" : {
				"OBJECTID" : "4319",
				"UniqueID" : "IF39-3624921",
				"WarningTitle" : "AVOID SMOKE - Mount Colliery (near Killarney) - fire as at  3:29pm Friday, 30 August 2024",
				"WarningLevel" : "Advice",
				"CallToAction" : "AVOID SMOKE",
				"WarningText" : "\nAVOID SMOKE - Mount Colliery (near Killarney) - fire as at  3:29pm Friday, 30 August 2024 \n\n \n\nWarning level: ADVICE\n\n \n\n\nWarning area: Mount Colliery and surrounding areas\n\n\n \n\nSmoke is currently affecting Mount Colliery and surrounding areas. This is from a fire burning near Sunday Plains Road, Mount Colliery.\n\n\n \n\nWhat you should do:\n\n- Stay inside and close windows and doors.\n\n- Keep respiratory medication close by.\n\n- Follow your bushfire survival plan now. If you do not have a bushfire survival plan, make one on the QFD website.\n\n- Avoid driving through smoke if you can.\n\n- Watch out for firefighters working in the area.\n\n- Do not fly drones around the fire. Drones affect air operations.\n\n\n\n \n\nImpacts:\n\n- No properties are at risk.\n\n- Smoke can make it hard for some people to breathe.\n\n- Smoke can make it hard to see when you are driving.\n\n- Some roads may be closed.\n\n\n\n \n\nFurther Information:\n\n- For all warnings, visit the QFD Current Bushfires and Warnings website.\n\n- Follow QFD on Facebook and X.com.\n\n- For road closures, visit the QLD Traffic website or call 13 19 40.\n\n- Visit the Department of Environment and Science website for live air quality data.\n\n- Find out how to get ready for a bushfire on the QFD website under Prepare - Bushfire.\n\n\n\n \n\nUpdates will be issued if the situation changes.\n\n \n\nThis warning is from Queensland Fire Department.\n\n",
				"Header" : "Smoke is currently affecting Mount Colliery and surrounding areas. This is from a fire burning near Sunday Plains Road, Mount Colliery.",
				"Impacts" : "- No properties are at risk.\r\n\r\n- Smoke can make it hard for some people to breathe.\r\n\r\n- Smoke can make it hard to see when you are driving.\r\n\r\n- Some roads may be closed.",
				"LeaveSafely" : null,
				"FurtherInformation" : "- For all warnings, visit the QFD Current Bushfires and Warnings website.\n\n- Follow QFD on Facebook and X.com.\n\n- For road closures, visit the QLD Traffic website or call 13 19 40.\n\n- Visit the Department of Environment and Science website for live air quality data.\n\n- Find out how to get ready for a bushfire on the QFD website under Prepare - Bushfire.\r\n\r\n\r\nUpdates will be issued if the situation changes.\r\n\r\nThis warning is from Queensland Fire Department.",
				"WarningLevelSort" : "7",
				"ShouldDo" : "- Stay inside and close windows and doors.\r\n\r\n- Keep respiratory medication close by.\r\n\r\n- Follow your bushfire survival plan now. If you do not have a bushfire survival plan, make one on the QFD website.\r\n\r\n- Avoid driving through smoke if you can.\r\n\r\n- Watch out for firefighters working in the area.\r\n\r\n- Do not fly drones around the fire. Drones affect air operations.",
				"WarningArea" : "Mount Colliery and surrounding areas",
				"Master_Incident_Number" : "QF3-24-104663",
				"CurrentStatus" : "Patrolled",
				"Location" : "SUNDAY PLAINS RD & GAMBUBAL RD",
				"Jurisdiction" : "3 South Western Region",
				"Latitude" : -28.283983557157,
				"Longitude" : 152.35274317842,
				"VehiclesAssigned" : "0",
				"VehiclesOnRoute" : "0",
				"VehiclesOnScene" : "0",
				"GroupedType" : "FIRE VEGETATION",
				"Locality" : "MOUNT COLLIERY",
				"ItemDateTimeUTM" : "20240830052600",
				"ItemDateTimeLocal_ISO" : "2024-08-30T15:26:00+10:00",
				"PublishDateLocal_ISO" : "2024-08-30T23:46:08+10:00",
				"ItemExpiryDateTimeLocal_ISO" : "2024-08-31T15:26:00+10:00"
			}
		},
		{
			"type" : "Feature",
			"geometry" : {
				"type" : "Polygon",
				"coordinates" : [
					[
						[ 149.9654173851, -26.7410114118, 0 ],
						[ 149.8053431511, -26.7151004038, 0 ],
						[ 149.805085659, -26.7149470667, 0 ],
						[ 149.7906661034, -26.820087771, 0 ],
						[ 149.9527144432, -26.8338745151, 0 ],
						[ 149.9654173851, -26.7410114118, 0 ]
					]
				]
			},
			"properties" : {
				"OBJECTID" : "4320",
				"UniqueID" : "IF39-3625321",
				"WarningTitle" : "AVOID SMOKE - South Drillham - fire as at  3:39pm Friday, 30 August 2024",
				"WarningLevel" : "Advice",
				"CallToAction" : "AVOID SMOKE",
				"WarningText" : "\nAVOID SMOKE - South Drillham - fire as at  3:39pm Friday, 30 August 2024 \n\n \n\nWarning level: ADVICE\n\n \n\n\nWarning area: South Drillham\n\n\n \n\nSmoke is currently affecting South Drillham. This is from a fire burning near Butlers Extension Road.\n\n\n \n\nWhat you should do:\n\n- Stay inside and close windows and doors.\n\n- Keep respiratory medication close by.\n\n- Follow your bushfire survival plan now. If you do not have a bushfire survival plan, make one on the QFD website.\n\n- Avoid driving through smoke if you can.\n\n- Watch out for firefighters working in the area.\n\n- Do not fly drones around the fire. Drones affect air operations.\n\n\n\n \n\nImpacts:\n\n- No properties are at risk.\n\n- Smoke can make it hard for some people to breathe.\n\n- Smoke can make it hard to see when you are driving.\n\n- Some roads may be closed.\n\n\n\n \n\nFurther Information:\n\n- For all warnings, visit the QFD Current Bushfires and Warnings website.\n\n- Follow QFD on Facebook and X.com.\n\n- For road closures, visit the QLD Traffic website or call 13 19 40.\n\n- Visit the Department of Environment and Science website for live air quality data.\n\n- Find out how to get ready for a bushfire on the QFD website under Prepare - Bushfire.\n\n\n\n \n\nUpdates will be issued if the situation changes.\n\n \n\nThis warning is from Queensland Fire Department.\n\n",
				"Header" : "Smoke is currently affecting South Drillham. This is from a fire burning near Butlers Extension Road.",
				"Impacts" : "- No properties are at risk.\r\n\r\n- Smoke can make it hard for some people to breathe.\r\n\r\n- Smoke can make it hard to see when you are driving.\r\n\r\n- Some roads may be closed.",
				"LeaveSafely" : null,
				"FurtherInformation" : "- For all warnings, visit the QFD Current Bushfires and Warnings website.\n\n- Follow QFD on Facebook and X.com.\n\n- For road closures, visit the QLD Traffic website or call 13 19 40.\n\n- Visit the Department of Environment and Science website for live air quality data.\n\n- Find out how to get ready for a bushfire on the QFD website under Prepare - Bushfire.\r\n\r\n\r\nUpdates will be issued if the situation changes.\r\n\r\nThis warning is from Queensland Fire Department.",
				"WarningLevelSort" : "7",
				"ShouldDo" : "- Stay inside and close windows and doors.\r\n\r\n- Keep respiratory medication close by.\r\n\r\n- Follow your bushfire survival plan now. If you do not have a bushfire survival plan, make one on the QFD website.\r\n\r\n- Avoid driving through smoke if you can.\r\n\r\n- Watch out for firefighters working in the area.\r\n\r\n- Do not fly drones around the fire. Drones affect air operations.",
				"WarningArea" : "South Drillham",
				"Master_Incident_Number" : "QF3-24-104699",
				"CurrentStatus" : "Patrolled",
				"Location" : "Butlers Extension Rd",
				"Jurisdiction" : "3 South Western Region",
				"Latitude" : -26.772587261096,
				"Longitude" : 149.87443685531,
				"VehiclesAssigned" : "0",
				"VehiclesOnRoute" : "0",
				"VehiclesOnScene" : "0",
				"GroupedType" : "FIRE VEGETATION",
				"Locality" : "DRILLHAM SOUTH",
				"ItemDateTimeUTM" : "20240830053700",
				"ItemDateTimeLocal_ISO" : "2024-08-30T15:37:00+10:00",
				"PublishDateLocal_ISO" : "2024-08-30T23:46:08+10:00",
				"ItemExpiryDateTimeLocal_ISO" : "2024-08-31T15:37:00+10:00"
			}
		},
		{
			"type" : "Feature",
			"geometry" : {
				"type" : "Polygon",
				"coordinates" : [
					[
						[ 152.9793392062, -26.9854428414, 0 ],
						[ 153.087142551, -26.996150316, 0 ],
						[ 153.116324985, -26.8639182201, 0 ],
						[ 153.025687778, -26.8531981872, 0 ],
						[ 153.0119548678, -26.8691247267, 0 ],
						[ 152.9944454074, -26.9254621599, 0 ],
						[ 152.9937587619, -26.9422966963, 0 ],
						[ 152.9793392062, -26.9854428414, 0 ]
					]
				]
			},
			"properties" : {
				"OBJECTID" : "4305",
				"UniqueID" : "IF39-3622221",
				"WarningTitle" : "AVOID SMOKE (HAZARD REDUCTION BURN) - Coochin Creek (near Caloundra) - fire as at 12:50pm Thursday, 29 August 2024",
				"WarningLevel" : "Advice",
				"CallToAction" : "AVOID SMOKE (HAZARD REDUCTION BURN)",
				"WarningText" : "AVOID SMOKE (HAZARD REDUCTION BURN) - Coochin Creek (near Caloundra) - fire as at 12:50pm Thursday, 29 August 2024 \n\n \n\nWarning level: ADVICE\n\n \n\n\nWarning area: Coochin Creek and surrounding areas\n\n\n \n\nSmoke is currently affecting Coochin Creek and surrounding areas. This is from a hazard reduction burn near Roys Road, Beerwah State Forest. This fire is under control.\n\n \n\nWhat you should do:\n\n- Stay inside and close windows and doors.\n\n- Keep respiratory medication close by.\n\n- Avoid driving through smoke if you can.\n\n- Watch out for firefighters working in the area.\n\n- Do not fly drones around the fire. Drones affect air operations.\n\n\n\n \n\nImpacts:\n\n- Smoke can make it hard for some people to breathe.\n\n- Smoke can make it hard to see when you are driving.\n\n- No properties are at risk.\n\n\n\n \n\nFurther Information:\n\n- For all warnings, visit the QFD Current Bushfires and Warnings website.\n\n- Follow QFD on Facebook and X.com.\n\n- For road closures, visit the QLD Traffic website or call 13 19 40.\n\n- Visit the Department of Environment and Science website for live air quality data.\n\n- Find out how to get ready for a bushfire on the QFD website under Prepare - Bushfire.\n\n\n\n \n\nUpdates will be issued if needed.\n\n \n\nThis warning is from Queensland Fire Department.\n\n",
				"Header" : "Smoke is currently affecting Coochin Creek and surrounding areas. This is from a hazard reduction burn near Roys Road, Beerwah State Forest. This fire is under control.",
				"Impacts" : "- Smoke can make it hard for some people to breathe.\r\n- Smoke can make it hard to see when you are driving.\r\n- No properties are at risk.",
				"LeaveSafely" : null,
				"FurtherInformation" : "- For all warnings, visit the QFD Current Bushfires and Warnings website.\n\n- Follow QFD on Facebook and X.com.\n\n- For road closures, visit the QLD Traffic website or call 13 19 40.\n\n- Visit the Department of Environment and Science website for live air quality data.\n\n- Find out how to get ready for a bushfire on the QFD website under Prepare - Bushfire.\r\n\r\n\r\nUpdates will be issued if needed.\r\n\r\nThis warning is from Queensland Fire Department.",
				"WarningLevelSort" : "8",
				"ShouldDo" : "- Stay inside and close windows and doors.\r\n\r\n- Keep respiratory medication close by.\r\n\r\n- Avoid driving through smoke if you can.\r\n\r\n- Watch out for firefighters working in the area.\r\n\r\n- Do not fly drones around the fire. Drones affect air operations.",
				"WarningArea" : "Coochin Creek and surrounding areas",
				"Latitude" : -26.931278011137,
				"Longitude" : 153.05040701628,
				"GroupedType" : "FIRE VEGETATION",
				"ItemDateTimeUTM" : "20240829025000",
				"ItemDateTimeLocal_ISO" : "2024-08-29T12:50:00+10:00",
				"PublishDateLocal_ISO" : "2024-08-30T23:46:08+10:00",
				"ItemExpiryDateTimeLocal_ISO" : "2024-08-30T12:50:00+10:00"
			}
		},
		{
			"type" : "Feature",
			"geometry" : {
				"type" : "Polygon",
				"coordinates" : [
					[
						[ 145.8141990689, -25.0370022343, 0 ],
						[ 146.5997215299, -26.1787765002, 0 ],
						[ 148.0856224088, -25.0817870259, 0 ],
						[ 147.4182029752, -24.3882970825, 0 ],
						[ 146.2454124478, -24.1830080384, 0 ],
						[ 145.8141990689, -25.0370022343, 0 ]
					]
				]
			},
			"properties" : {
				"OBJECTID" : "4306",
				"UniqueID" : "IF39-3622421",
				"WarningTitle" : "AVOID SMOKE (HAZARD REDUCTION BURN) - Mount Playfair (near Carnarvon National Park) - fire as at  3:01pm Thursday, 29 August 2024",
				"WarningLevel" : "Advice",
				"CallToAction" : "AVOID SMOKE (HAZARD REDUCTION BURN)",
				"WarningText" : "\nAVOID SMOKE (HAZARD REDUCTION BURN) - Mount Playfair (near Carnarvon National Park) - fire as at  3:01pm Thursday, 29 August 2024 \n\n \n\nWarning level: ADVICE\n\n \n\n\nWarning area: Mount Playfair, Tambo, Yandarlo and surrounding areas\n\n\n \n\nSmoke is currently affecting Mount Playfair, Tambo, Yandarlo and surrounding areas. This is from a hazard reduction burn in the Carnarvon National Park. This fire is under control. This is a multi-agency hazard reduction burn with Queensland Parks and Wildlife.\n\n\n\n\n \n\nWhat you should do:\n\n- Stay inside and close windows and doors.\n\n- Keep respiratory medication close by.\n\n- Avoid driving through smoke if you can.\n\n- Watch out for firefighters working in the area.\n\n- Do not fly drones around the fire. Drones affect air operations.\n\n\n\n \n\nImpacts:\n\n- Smoke can make it hard for some people to breathe.\n\n- Smoke can make it hard to see when you are driving.\n\n- No properties are at risk.\n\n\n\n \n\nFurther Information:\n\n- For all warnings, visit the QFD Current Bushfires and Warnings website.\n\n- Follow QFD on Facebook and X.com.\n\n- For road closures, visit the QLD Traffic website or call 13 19 40.\n\n- Visit the Department of Environment and Science website for live air quality data.\n\n- Find out how to get ready for a bushfire on the QFD website under Prepare - Bushfire.\n\n\n\n \n\nUpdates will be issued if needed.\n\n \n\nThis warning is from Queensland Fire Department.\n\n",
				"Header" : "Smoke is currently affecting Mount Playfair, Tambo, Yandarlo and surrounding areas. This is from a hazard reduction burn in the Carnarvon National Park. This fire is under control. This is a multi-agency hazard reduction burn with Queensland Parks and Wildlife.",
				"Impacts" : "- Smoke can make it hard for some people to breathe.\n\n- Smoke can make it hard to see when you are driving.\n\n- No properties are at risk.",
				"LeaveSafely" : null,
				"FurtherInformation" : "- For all warnings, visit the QFD Current Bushfires and Warnings website.\n\n- Follow QFD on Facebook and X.com.\n\n- For road closures, visit the QLD Traffic website or call 13 19 40.\n\n- Visit the Department of Environment and Science website for live air quality data.\n\n- Find out how to get ready for a bushfire on the QFD website under Prepare - Bushfire.\r\n\r\n\r\nUpdates will be issued if needed.\n\n \n\nThis warning is from Queensland Fire Department.",
				"WarningLevelSort" : "8",
				"ShouldDo" : "- Stay inside and close windows and doors.\n\n- Keep respiratory medication close by.\n\n- Avoid driving through smoke if you can.\n\n- Watch out for firefighters working in the area.\n\n- Do not fly drones around the fire. Drones affect air operations.",
				"WarningArea" : "Mount Playfair, Tambo, Yandarlo and surrounding areas",
				"Latitude" : -25.13650174911,
				"Longitude" : 146.76726303376,
				"GroupedType" : "FIRE VEGETATION",
				"ItemDateTimeUTM" : "20240829050100",
				"ItemDateTimeLocal_ISO" : "2024-08-29T15:01:00+10:00",
				"PublishDateLocal_ISO" : "2024-08-30T23:46:08+10:00",
				"ItemExpiryDateTimeLocal_ISO" : "2024-08-30T15:01:00+10:00"
			}
		},
		{
			"type" : "Feature",
			"geometry" : {
				"type" : "Point",
				"coordinates" : [ 145.404607, -17.271004 ]
			},
			"properties" : {
				"OBJECTID" : "69852",
				"UniqueID" : "QF7-24-099261",
				"WarningTitle" : "Information - WATSONVILLE",
				"WarningLevel" : "Information",
				"CallToAction" : "There is a vegetation fire at this location. Smoke may affect residents and motorists in the area. Residents should close their doors and windows and keep medication close by if suffering from a respiratory condition. Motorists should use caution and drive to conditions. If you believe your property is under threat, you should call Triple Zero (000) immediately.",
				"WarningText" : "There is a vegetation fire at this location. Smoke may affect residents and motorists in the area. Residents should close their doors and windows and keep medication close by if suffering from a respiratory condition. Motorists should use caution and drive to conditions. If you believe your property is under threat, you should call Triple Zero (000) immediately.",
				"Header" : "There is a vegetation fire at this location. Smoke may affect residents and motorists in the area. Residents should close their doors and windows and keep medication close by if suffering from a respiratory condition. Motorists should use caution and drive to conditions. If you believe your property is under threat, you should call Triple Zero (000) immediately.",
				"WarningLevelSort" : "100",
				"WarningArea" : "WATSONVILLE",
				"CurrentStatus" : "Patrolled",
				"Location" : "Mount Wallum Rd",
				"Jurisdiction" : "7 Far Northern Region",
				"Latitude" : -17.271004,
				"Longitude" : 145.404607,
				"VehiclesAssigned" : "0",
				"VehiclesOnRoute" : "0",
				"VehiclesOnScene" : "0",
				"GroupedType" : "FIRE PERMITTED BURN",
				"Locality" : "WATSONVILLE",
				"ItemDateTimeUTM" : "20240821120147",
				"ItemDateTimeLocal_ISO" : "2024-08-21T22:01:47+10:00",
				"PublishDateLocal_ISO" : "2024-08-30T23:46:08+10:00",
				"ItemExpiryDateTimeLocal_ISO" : "2024-08-22T22:01:47+10:00"
			}
		},
		{
			"type" : "Feature",
			"geometry" : {
				"type" : "Point",
				"coordinates" : [ 145.317825, -17.009957 ]
			},
			"properties" : {
				"OBJECTID" : "70559",
				"UniqueID" : "QF7-24-100664",
				"WarningTitle" : "Information - PADDYS GREEN",
				"WarningLevel" : "Information",
				"CallToAction" : "There is a vegetation fire at this location. Smoke may affect residents and motorists in the area. Residents should close their doors and windows and keep medication close by if suffering from a respiratory condition. Motorists should use caution and drive to conditions. If you believe your property is under threat, you should call Triple Zero (000) immediately.",
				"WarningText" : "There is a vegetation fire at this location. Smoke may affect residents and motorists in the area. Residents should close their doors and windows and keep medication close by if suffering from a respiratory condition. Motorists should use caution and drive to conditions. If you believe your property is under threat, you should call Triple Zero (000) immediately.",
				"Header" : "There is a vegetation fire at this location. Smoke may affect residents and motorists in the area. Residents should close their doors and windows and keep medication close by if suffering from a respiratory condition. Motorists should use caution and drive to conditions. If you believe your property is under threat, you should call Triple Zero (000) immediately.",
				"WarningLevelSort" : "100",
				"WarningArea" : "PADDYS GREEN",
				"CurrentStatus" : "Patrolled",
				"Location" : "Tyrconnell Rd",
				"Jurisdiction" : "7 Far Northern Region",
				"Latitude" : -17.009957,
				"Longitude" : 145.317825,
				"VehiclesAssigned" : "0",
				"VehiclesOnRoute" : "0",
				"VehiclesOnScene" : "0",
				"GroupedType" : "FIRE VEGETATION",
				"Locality" : "PADDYS GREEN",
				"ItemDateTimeUTM" : "20240823125601",
				"ItemDateTimeLocal_ISO" : "2024-08-23T22:56:01+10:00",
				"PublishDateLocal_ISO" : "2024-08-30T23:46:08+10:00",
				"ItemExpiryDateTimeLocal_ISO" : "2024-08-24T22:56:01+10:00"
			}
		},
		{
			"type" : "Feature",
			"geometry" : {
				"type" : "Point",
				"coordinates" : [ 145.792742, -17.106799 ]
			},
			"properties" : {
				"OBJECTID" : "72010",
				"UniqueID" : "QF7-24-103326",
				"WarningTitle" : "Information - ALOOMBA",
				"WarningLevel" : "Information",
				"CallToAction" : "There is a vegetation fire at this location. Smoke may affect residents and motorists in the area. Residents should close their doors and windows and keep medication close by if suffering from a respiratory condition. Motorists should use caution and drive to conditions. If you believe your property is under threat, you should call Triple Zero (000) immediately.",
				"WarningText" : "There is a vegetation fire at this location. Smoke may affect residents and motorists in the area. Residents should close their doors and windows and keep medication close by if suffering from a respiratory condition. Motorists should use caution and drive to conditions. If you believe your property is under threat, you should call Triple Zero (000) immediately.",
				"Header" : "There is a vegetation fire at this location. Smoke may affect residents and motorists in the area. Residents should close their doors and windows and keep medication close by if suffering from a respiratory condition. Motorists should use caution and drive to conditions. If you believe your property is under threat, you should call Triple Zero (000) immediately.",
				"WarningLevelSort" : "100",
				"WarningArea" : "ALOOMBA",
				"CurrentStatus" : "Patrolled",
				"Location" : "Moss Accs",
				"Jurisdiction" : "7 Far Northern Region",
				"Latitude" : -17.106799,
				"Longitude" : 145.792742,
				"VehiclesAssigned" : "0",
				"VehiclesOnRoute" : "0",
				"VehiclesOnScene" : "0",
				"GroupedType" : "FIRE PERMITTED BURN",
				"Locality" : "ALOOMBA",
				"ItemDateTimeUTM" : "20240827121408",
				"ItemDateTimeLocal_ISO" : "2024-08-27T22:14:08+10:00",
				"PublishDateLocal_ISO" : "2024-08-30T23:46:08+10:00",
				"ItemExpiryDateTimeLocal_ISO" : "2024-08-28T22:14:08+10:00"
			}
		},
		{
			"type" : "Feature",
			"geometry" : {
				"type" : "Point",
				"coordinates" : [ 152.023358, -26.361976 ]
			},
			"properties" : {
				"OBJECTID" : "72014",
				"UniqueID" : "QF4-24-103464",
				"WarningTitle" : "Information - BARAMBAH",
				"WarningLevel" : "Information",
				"CallToAction" : "There is a vegetation fire at this location. Smoke may affect residents and motorists in the area. Residents should close their doors and windows and keep medication close by if suffering from a respiratory condition. Motorists should use caution and drive to conditions. If you believe your property is under threat, you should call Triple Zero (000) immediately.",
				"WarningText" : "There is a vegetation fire at this location. Smoke may affect residents and motorists in the area. Residents should close their doors and windows and keep medication close by if suffering from a respiratory condition. Motorists should use caution and drive to conditions. If you believe your property is under threat, you should call Triple Zero (000) immediately.",
				"Header" : "There is a vegetation fire at this location. Smoke may affect residents and motorists in the area. Residents should close their doors and windows and keep medication close by if suffering from a respiratory condition. Motorists should use caution and drive to conditions. If you believe your property is under threat, you should call Triple Zero (000) immediately.",
				"WarningLevelSort" : "100",
				"WarningArea" : "BARAMBAH",
				"CurrentStatus" : "Patrolled",
				"Location" : "Silver Perch Rd",
				"Jurisdiction" : "4 North Coast Region",
				"Latitude" : -26.361976,
				"Longitude" : 152.023358,
				"VehiclesAssigned" : "0",
				"VehiclesOnRoute" : "0",
				"VehiclesOnScene" : "0",
				"GroupedType" : "FIRE VEGETATION",
				"Locality" : "BARAMBAH",
				"ItemDateTimeUTM" : "20240827163925",
				"ItemDateTimeLocal_ISO" : "2024-08-28T02:39:25+10:00",
				"PublishDateLocal_ISO" : "2024-08-30T23:46:08+10:00",
				"ItemExpiryDateTimeLocal_ISO" : "2024-08-29T02:39:25+10:00"
			}
		},
		{
			"type" : "Feature",
			"geometry" : {
				"type" : "Point",
				"coordinates" : [ 152.831916, -27.941148 ]
			},
			"properties" : {
				"OBJECTID" : "72067",
				"UniqueID" : "QF6-24-104054",
				"WarningTitle" : "Information - WYARALONG",
				"WarningLevel" : "Information",
				"CallToAction" : "There is a vegetation fire at this location. Smoke may affect residents and motorists in the area. Residents should close their doors and windows and keep medication close by if suffering from a respiratory condition. Motorists should use caution and drive to conditions. If you believe your property is under threat, you should call Triple Zero (000) immediately.",
				"WarningText" : "There is a vegetation fire at this location. Smoke may affect residents and motorists in the area. Residents should close their doors and windows and keep medication close by if suffering from a respiratory condition. Motorists should use caution and drive to conditions. If you believe your property is under threat, you should call Triple Zero (000) immediately.",
				"Header" : "There is a vegetation fire at this location. Smoke may affect residents and motorists in the area. Residents should close their doors and windows and keep medication close by if suffering from a respiratory condition. Motorists should use caution and drive to conditions. If you believe your property is under threat, you should call Triple Zero (000) immediately.",
				"WarningLevelSort" : "100",
				"WarningArea" : "WYARALONG",
				"CurrentStatus" : "Patrolled",
				"Location" : "BEAUDESERT BOONAH RD",
				"Jurisdiction" : "6 South Eastern Region",
				"Latitude" : -27.941148,
				"Longitude" : 152.831916,
				"VehiclesAssigned" : "0",
				"VehiclesOnRoute" : "0",
				"VehiclesOnScene" : "0",
				"GroupedType" : "FIRE VEGETATION",
				"Locality" : "WYARALONG",
				"ItemDateTimeUTM" : "20240828173046",
				"ItemDateTimeLocal_ISO" : "2024-08-29T03:30:46+10:00",
				"PublishDateLocal_ISO" : "2024-08-30T23:46:08+10:00",
				"ItemExpiryDateTimeLocal_ISO" : "2024-08-30T03:30:46+10:00"
			}
		},
		{
			"type" : "Feature",
			"geometry" : {
				"type" : "Point",
				"coordinates" : [ 144.435993, -20.411143 ]
			},
			"properties" : {
				"OBJECTID" : "72086",
				"UniqueID" : "QF1-24-104091",
				"WarningTitle" : "Information - PORCUPINE",
				"WarningLevel" : "Information",
				"CallToAction" : "There is a vegetation fire at this location. Smoke may affect residents and motorists in the area. Residents should close their doors and windows and keep medication close by if suffering from a respiratory condition. Motorists should use caution and drive to conditions. If you believe your property is under threat, you should call Triple Zero (000) immediately.",
				"WarningText" : "There is a vegetation fire at this location. Smoke may affect residents and motorists in the area. Residents should close their doors and windows and keep medication close by if suffering from a respiratory condition. Motorists should use caution and drive to conditions. If you believe your property is under threat, you should call Triple Zero (000) immediately.",
				"Header" : "There is a vegetation fire at this location. Smoke may affect residents and motorists in the area. Residents should close their doors and windows and keep medication close by if suffering from a respiratory condition. Motorists should use caution and drive to conditions. If you believe your property is under threat, you should call Triple Zero (000) immediately.",
				"WarningLevelSort" : "100",
				"WarningArea" : "PORCUPINE",
				"CurrentStatus" : "Patrolled",
				"Location" : "PORCUPINE GORGE LOOKOUT ACCS",
				"Jurisdiction" : "1 Northern Region",
				"Latitude" : -20.411143,
				"Longitude" : 144.435993,
				"VehiclesAssigned" : "0",
				"VehiclesOnRoute" : "0",
				"VehiclesOnScene" : "0",
				"GroupedType" : "FIRE VEGETATION",
				"Locality" : "PORCUPINE",
				"ItemDateTimeUTM" : "20240828182027",
				"ItemDateTimeLocal_ISO" : "2024-08-29T04:20:27+10:00",
				"PublishDateLocal_ISO" : "2024-08-30T23:46:08+10:00",
				"ItemExpiryDateTimeLocal_ISO" : "2024-08-30T04:20:27+10:00"
			}
		},
		{
			"type" : "Feature",
			"geometry" : {
				"type" : "Point",
				"coordinates" : [ 152.868669, -25.373017 ]
			},
			"properties" : {
				"OBJECTID" : "72157",
				"UniqueID" : "QF4-24-104253",
				"WarningTitle" : "Information - BOORAL",
				"WarningLevel" : "Information",
				"CallToAction" : "There is a vegetation fire at this location. Smoke may affect residents and motorists in the area. Residents should close their doors and windows and keep medication close by if suffering from a respiratory condition. Motorists should use caution and drive to conditions. If you believe your property is under threat, you should call Triple Zero (000) immediately.",
				"WarningText" : "There is a vegetation fire at this location. Smoke may affect residents and motorists in the area. Residents should close their doors and windows and keep medication close by if suffering from a respiratory condition. Motorists should use caution and drive to conditions. If you believe your property is under threat, you should call Triple Zero (000) immediately.",
				"Header" : "There is a vegetation fire at this location. Smoke may affect residents and motorists in the area. Residents should close their doors and windows and keep medication close by if suffering from a respiratory condition. Motorists should use caution and drive to conditions. If you believe your property is under threat, you should call Triple Zero (000) immediately.",
				"WarningLevelSort" : "100",
				"WarningArea" : "BOORAL",
				"CurrentStatus" : "Patrolled",
				"Location" : "Wheeley Rd",
				"Jurisdiction" : "4 North Coast Region",
				"Latitude" : -25.373017,
				"Longitude" : 152.868669,
				"VehiclesAssigned" : "0",
				"VehiclesOnRoute" : "0",
				"VehiclesOnScene" : "0",
				"GroupedType" : "FIRE PERMITTED BURN",
				"Locality" : "BOORAL",
				"ItemDateTimeUTM" : "20240828215015",
				"ItemDateTimeLocal_ISO" : "2024-08-29T07:50:15+10:00",
				"PublishDateLocal_ISO" : "2024-08-30T23:46:08+10:00",
				"ItemExpiryDateTimeLocal_ISO" : "2024-08-30T07:50:15+10:00"
			}
		},
		{
			"type" : "Feature",
			"geometry" : {
				"type" : "Point",
				"coordinates" : [ 152.275233, -27.221181 ]
			},
			"properties" : {
				"OBJECTID" : "72288",
				"UniqueID" : "QF6-24-104448",
				"WarningTitle" : "Information - BIARRA",
				"WarningLevel" : "Information",
				"CallToAction" : "There is a vegetation fire at this location. Smoke may affect residents and motorists in the area. Residents should close their doors and windows and keep medication close by if suffering from a respiratory condition. Motorists should use caution and drive to conditions. If you believe your property is under threat, you should call Triple Zero (000) immediately.",
				"WarningText" : "There is a vegetation fire at this location. Smoke may affect residents and motorists in the area. Residents should close their doors and windows and keep medication close by if suffering from a respiratory condition. Motorists should use caution and drive to conditions. If you believe your property is under threat, you should call Triple Zero (000) immediately.",
				"Header" : "There is a vegetation fire at this location. Smoke may affect residents and motorists in the area. Residents should close their doors and windows and keep medication close by if suffering from a respiratory condition. Motorists should use caution and drive to conditions. If you believe your property is under threat, you should call Triple Zero (000) immediately.",
				"WarningLevelSort" : "100",
				"WarningArea" : "BIARRA",
				"CurrentStatus" : "Patrolled",
				"Location" : "Cressbrook Creek Rd",
				"Jurisdiction" : "6 South Eastern Region",
				"Latitude" : -27.221181,
				"Longitude" : 152.275233,
				"VehiclesAssigned" : "0",
				"VehiclesOnRoute" : "0",
				"VehiclesOnScene" : "0",
				"GroupedType" : "FIRE VEGETATION",
				"Locality" : "BIARRA",
				"ItemDateTimeUTM" : "20240829121143",
				"ItemDateTimeLocal_ISO" : "2024-08-29T22:11:43+10:00",
				"PublishDateLocal_ISO" : "2024-08-30T23:46:08+10:00",
				"ItemExpiryDateTimeLocal_ISO" : "2024-08-30T22:11:43+10:00"
			}
		},
		{
			"type" : "Feature",
			"geometry" : {
				"type" : "Point",
				"coordinates" : [ 152.9993, -26.697933 ]
			},
			"properties" : {
				"OBJECTID" : "72293",
				"UniqueID" : "QF4-24-104458",
				"WarningTitle" : "Information - CHEVALLUM",
				"WarningLevel" : "Information",
				"CallToAction" : "There is a vegetation fire at this location. Smoke may affect residents and motorists in the area. Residents should close their doors and windows and keep medication close by if suffering from a respiratory condition. Motorists should use caution and drive to conditions. If you believe your property is under threat, you should call Triple Zero (000) immediately.",
				"WarningText" : "There is a vegetation fire at this location. Smoke may affect residents and motorists in the area. Residents should close their doors and windows and keep medication close by if suffering from a respiratory condition. Motorists should use caution and drive to conditions. If you believe your property is under threat, you should call Triple Zero (000) immediately.",
				"Header" : "There is a vegetation fire at this location. Smoke may affect residents and motorists in the area. Residents should close their doors and windows and keep medication close by if suffering from a respiratory condition. Motorists should use caution and drive to conditions. If you believe your property is under threat, you should call Triple Zero (000) immediately.",
				"WarningLevelSort" : "100",
				"WarningArea" : "CHEVALLUM",
				"CurrentStatus" : "Patrolled",
				"Location" : "Chevallum Rd",
				"Jurisdiction" : "4 North Coast Region",
				"Latitude" : -26.697933,
				"Longitude" : 152.9993,
				"VehiclesAssigned" : "0",
				"VehiclesOnRoute" : "0",
				"VehiclesOnScene" : "0",
				"GroupedType" : "FIRE PERMITTED BURN",
				"Locality" : "CHEVALLUM",
				"ItemDateTimeUTM" : "20240829123028.29",
				"ItemDateTimeLocal_ISO" : "2024-08-29T22:30:28+10:00",
				"PublishDateLocal_ISO" : "2024-08-30T23:46:08+10:00",
				"ItemExpiryDateTimeLocal_ISO" : "2024-08-30T22:30:28.29+10:00"
			}
		},
		{
			"type" : "Feature",
			"geometry" : {
				"type" : "Point",
				"coordinates" : [ 151.714779, -24.742098 ]
			},
			"properties" : {
				"OBJECTID" : "72307",
				"UniqueID" : "QF4-24-104476",
				"WarningTitle" : "Information - KOLONGA",
				"WarningLevel" : "Information",
				"CallToAction" : "There is a vegetation fire at this location. Smoke may affect residents and motorists in the area. Residents should close their doors and windows and keep medication close by if suffering from a respiratory condition. Motorists should use caution and drive to conditions. If you believe your property is under threat, you should call Triple Zero (000) immediately.",
				"WarningText" : "There is a vegetation fire at this location. Smoke may affect residents and motorists in the area. Residents should close their doors and windows and keep medication close by if suffering from a respiratory condition. Motorists should use caution and drive to conditions. If you believe your property is under threat, you should call Triple Zero (000) immediately.",
				"Header" : "There is a vegetation fire at this location. Smoke may affect residents and motorists in the area. Residents should close their doors and windows and keep medication close by if suffering from a respiratory condition. Motorists should use caution and drive to conditions. If you believe your property is under threat, you should call Triple Zero (000) immediately.",
				"WarningLevelSort" : "100",
				"WarningArea" : "KOLONGA",
				"CurrentStatus" : "Patrolled",
				"Location" : "BRUCE HWY & BARTON RD",
				"Jurisdiction" : "4 North Coast Region",
				"Latitude" : -24.742098,
				"Longitude" : 151.714779,
				"VehiclesAssigned" : "0",
				"VehiclesOnRoute" : "0",
				"VehiclesOnScene" : "0",
				"GroupedType" : "FIRE PERMITTED BURN",
				"Locality" : "KOLONGA",
				"ItemDateTimeUTM" : "20240829131508",
				"ItemDateTimeLocal_ISO" : "2024-08-29T23:15:08+10:00",
				"PublishDateLocal_ISO" : "2024-08-30T23:46:08+10:00",
				"ItemExpiryDateTimeLocal_ISO" : "2024-08-30T23:15:08+10:00"
			}
		},
		{
			"type" : "Feature",
			"geometry" : {
				"type" : "Point",
				"coordinates" : [ 151.830203, -26.979952 ]
			},
			"properties" : {
				"OBJECTID" : "72342",
				"UniqueID" : "QF3-24-101955",
				"WarningTitle" : "Information - COOYAR",
				"WarningLevel" : "Information",
				"CallToAction" : "There is a vegetation fire at this location. Smoke may affect residents and motorists in the area. Residents should close their doors and windows and keep medication close by if suffering from a respiratory condition. Motorists should use caution and drive to conditions. If you believe your property is under threat, you should call Triple Zero (000) immediately.",
				"WarningText" : "There is a vegetation fire at this location. Smoke may affect residents and motorists in the area. Residents should close their doors and windows and keep medication close by if suffering from a respiratory condition. Motorists should use caution and drive to conditions. If you believe your property is under threat, you should call Triple Zero (000) immediately.",
				"Header" : "There is a vegetation fire at this location. Smoke may affect residents and motorists in the area. Residents should close their doors and windows and keep medication close by if suffering from a respiratory condition. Motorists should use caution and drive to conditions. If you believe your property is under threat, you should call Triple Zero (000) immediately.",
				"WarningLevelSort" : "100",
				"WarningArea" : "COOYAR",
				"CurrentStatus" : "Patrolled",
				"Location" : "PALMS RD & NEW ENGLAND HWY",
				"Jurisdiction" : "3 South Western Region",
				"Latitude" : -26.979952,
				"Longitude" : 151.830203,
				"VehiclesAssigned" : "0",
				"VehiclesOnRoute" : "0",
				"VehiclesOnScene" : "0",
				"GroupedType" : "FIRE VEGETATION",
				"Locality" : "COOYAR",
				"ItemDateTimeUTM" : "20240824203226",
				"ItemDateTimeLocal_ISO" : "2024-08-25T06:32:26+10:00",
				"PublishDateLocal_ISO" : "2024-08-30T23:46:08+10:00",
				"ItemExpiryDateTimeLocal_ISO" : "2024-08-26T06:32:26+10:00"
			}
		},
		{
			"type" : "Feature",
			"geometry" : {
				"type" : "Point",
				"coordinates" : [ 151.859603, -28.728557 ]
			},
			"properties" : {
				"OBJECTID" : "72372",
				"UniqueID" : "QF3-24-104624",
				"WarningTitle" : "Information - GLEN APLIN",
				"WarningLevel" : "Information",
				"CallToAction" : "There is a vegetation fire at this location. Smoke may affect residents and motorists in the area. Residents should close their doors and windows and keep medication close by if suffering from a respiratory condition. Motorists should use caution and drive to conditions. If you believe your property is under threat, you should call Triple Zero (000) immediately.",
				"WarningText" : "There is a vegetation fire at this location. Smoke may affect residents and motorists in the area. Residents should close their doors and windows and keep medication close by if suffering from a respiratory condition. Motorists should use caution and drive to conditions. If you believe your property is under threat, you should call Triple Zero (000) immediately.",
				"Header" : "There is a vegetation fire at this location. Smoke may affect residents and motorists in the area. Residents should close their doors and windows and keep medication close by if suffering from a respiratory condition. Motorists should use caution and drive to conditions. If you believe your property is under threat, you should call Triple Zero (000) immediately.",
				"WarningLevelSort" : "100",
				"WarningArea" : "GLEN APLIN",
				"CurrentStatus" : "Patrolled",
				"Location" : "COLLINS RD",
				"Jurisdiction" : "3 South Western Region",
				"Latitude" : -28.728557,
				"Longitude" : 151.859603,
				"VehiclesAssigned" : "0",
				"VehiclesOnRoute" : "0",
				"VehiclesOnScene" : "0",
				"GroupedType" : "FIRE VEGETATION",
				"Locality" : "GLEN APLIN",
				"ItemDateTimeUTM" : "20240829165856",
				"ItemDateTimeLocal_ISO" : "2024-08-30T02:58:56+10:00",
				"PublishDateLocal_ISO" : "2024-08-30T23:46:08+10:00",
				"ItemExpiryDateTimeLocal_ISO" : "2024-08-31T02:58:56+10:00"
			}
		},
		{
			"type" : "Feature",
			"geometry" : {
				"type" : "Point",
				"coordinates" : [ 152.152911, -26.823981 ]
			},
			"properties" : {
				"OBJECTID" : "72398",
				"UniqueID" : "QF4-24-104674",
				"WarningTitle" : "Information - TAROMEO",
				"WarningLevel" : "Information",
				"CallToAction" : "There is a vegetation fire at this location. Smoke may affect residents and motorists in the area. Residents should close their doors and windows and keep medication close by if suffering from a respiratory condition. Motorists should use caution and drive to conditions. If you believe your property is under threat, you should call Triple Zero (000) immediately.",
				"WarningText" : "There is a vegetation fire at this location. Smoke may affect residents and motorists in the area. Residents should close their doors and windows and keep medication close by if suffering from a respiratory condition. Motorists should use caution and drive to conditions. If you believe your property is under threat, you should call Triple Zero (000) immediately.",
				"Header" : "There is a vegetation fire at this location. Smoke may affect residents and motorists in the area. Residents should close their doors and windows and keep medication close by if suffering from a respiratory condition. Motorists should use caution and drive to conditions. If you believe your property is under threat, you should call Triple Zero (000) immediately.",
				"WarningLevelSort" : "100",
				"WarningArea" : "TAROMEO",
				"CurrentStatus" : "Patrolled",
				"Location" : "Old Esk Rd",
				"Jurisdiction" : "4 North Coast Region",
				"Latitude" : -26.823981,
				"Longitude" : 152.152911,
				"VehiclesAssigned" : "0",
				"VehiclesOnRoute" : "0",
				"VehiclesOnScene" : "0",
				"GroupedType" : "FIRE VEGETATION",
				"Locality" : "TAROMEO",
				"ItemDateTimeUTM" : "20240829180712",
				"ItemDateTimeLocal_ISO" : "2024-08-30T04:07:12+10:00",
				"PublishDateLocal_ISO" : "2024-08-30T23:46:08+10:00",
				"ItemExpiryDateTimeLocal_ISO" : "2024-08-31T04:07:12+10:00"
			}
		},
		{
			"type" : "Feature",
			"geometry" : {
				"type" : "Point",
				"coordinates" : [ 145.453505, -16.852924 ]
			},
			"properties" : {
				"OBJECTID" : "72423",
				"UniqueID" : "QF7-24-104711",
				"WarningTitle" : "Information - BIBOOHRA",
				"WarningLevel" : "Information",
				"CallToAction" : "There is a vegetation fire at this location. Smoke may affect residents and motorists in the area. Residents should close their doors and windows and keep medication close by if suffering from a respiratory condition. Motorists should use caution and drive to conditions. If you believe your property is under threat, you should call Triple Zero (000) immediately.",
				"WarningText" : "There is a vegetation fire at this location. Smoke may affect residents and motorists in the area. Residents should close their doors and windows and keep medication close by if suffering from a respiratory condition. Motorists should use caution and drive to conditions. If you believe your property is under threat, you should call Triple Zero (000) immediately.",
				"Header" : "There is a vegetation fire at this location. Smoke may affect residents and motorists in the area. Residents should close their doors and windows and keep medication close by if suffering from a respiratory condition. Motorists should use caution and drive to conditions. If you believe your property is under threat, you should call Triple Zero (000) immediately.",
				"WarningLevelSort" : "100",
				"WarningArea" : "BIBOOHRA",
				"CurrentStatus" : "Patrolled",
				"Location" : "Bilwon Rd",
				"Jurisdiction" : "7 Far Northern Region",
				"Latitude" : -16.852924,
				"Longitude" : 145.453505,
				"VehiclesAssigned" : "0",
				"VehiclesOnRoute" : "0",
				"VehiclesOnScene" : "0",
				"GroupedType" : "FIRE VEGETATION",
				"Locality" : "BIBOOHRA",
				"ItemDateTimeUTM" : "20240829185407",
				"ItemDateTimeLocal_ISO" : "2024-08-30T04:54:07+10:00",
				"PublishDateLocal_ISO" : "2024-08-30T23:46:08+10:00",
				"ItemExpiryDateTimeLocal_ISO" : "2024-08-31T04:54:07+10:00"
			}
		},
		{
			"type" : "Feature",
			"geometry" : {
				"type" : "Point",
				"coordinates" : [ 147.847798, -20.753227 ]
			},
			"properties" : {
				"OBJECTID" : "72449",
				"UniqueID" : "QF1-24-104722",
				"WarningTitle" : "Information - SPRINGLANDS",
				"WarningLevel" : "Information",
				"CallToAction" : "There is a vegetation fire at this location. Smoke may affect residents and motorists in the area. Residents should close their doors and windows and keep medication close by if suffering from a respiratory condition. Motorists should use caution and drive to conditions. If you believe your property is under threat, you should call Triple Zero (000) immediately.",
				"WarningText" : "There is a vegetation fire at this location. Smoke may affect residents and motorists in the area. Residents should close their doors and windows and keep medication close by if suffering from a respiratory condition. Motorists should use caution and drive to conditions. If you believe your property is under threat, you should call Triple Zero (000) immediately.",
				"Header" : "There is a vegetation fire at this location. Smoke may affect residents and motorists in the area. Residents should close their doors and windows and keep medication close by if suffering from a respiratory condition. Motorists should use caution and drive to conditions. If you believe your property is under threat, you should call Triple Zero (000) immediately.",
				"WarningLevelSort" : "100",
				"WarningArea" : "SPRINGLANDS",
				"CurrentStatus" : "Patrolled",
				"Location" : "BOWEN RIVER",
				"Jurisdiction" : "1 Northern Region",
				"Latitude" : -20.753227,
				"Longitude" : 147.847798,
				"VehiclesAssigned" : "0",
				"VehiclesOnRoute" : "0",
				"VehiclesOnScene" : "0",
				"GroupedType" : "FIRE VEGETATION",
				"Locality" : "SPRINGLANDS",
				"ItemDateTimeUTM" : "20240829190919",
				"ItemDateTimeLocal_ISO" : "2024-08-30T05:09:19+10:00",
				"PublishDateLocal_ISO" : "2024-08-30T23:46:08+10:00",
				"ItemExpiryDateTimeLocal_ISO" : "2024-08-31T05:09:19+10:00"
			}
		},
		{
			"type" : "Feature",
			"geometry" : {
				"type" : "Point",
				"coordinates" : [ 151.652683, -25.189609 ]
			},
			"properties" : {
				"OBJECTID" : "72456",
				"UniqueID" : "QF4-24-104798",
				"WarningTitle" : "Information - MOUNT PERRY",
				"WarningLevel" : "Information",
				"CallToAction" : "There is a vegetation fire at this location. Smoke may affect residents and motorists in the area. Residents should close their doors and windows and keep medication close by if suffering from a respiratory condition. Motorists should use caution and drive to conditions. If you believe your property is under threat, you should call Triple Zero (000) immediately.",
				"WarningText" : "There is a vegetation fire at this location. Smoke may affect residents and motorists in the area. Residents should close their doors and windows and keep medication close by if suffering from a respiratory condition. Motorists should use caution and drive to conditions. If you believe your property is under threat, you should call Triple Zero (000) immediately.",
				"Header" : "There is a vegetation fire at this location. Smoke may affect residents and motorists in the area. Residents should close their doors and windows and keep medication close by if suffering from a respiratory condition. Motorists should use caution and drive to conditions. If you believe your property is under threat, you should call Triple Zero (000) immediately.",
				"WarningLevelSort" : "100",
				"WarningArea" : "MOUNT PERRY",
				"CurrentStatus" : "Patrolled",
				"Location" : "Kapunda St & Spicer St",
				"Jurisdiction" : "4 North Coast Region",
				"Latitude" : -25.189609,
				"Longitude" : 151.652683,
				"VehiclesAssigned" : "0",
				"VehiclesOnRoute" : "0",
				"VehiclesOnScene" : "0",
				"GroupedType" : "FIRE PERMITTED BURN",
				"Locality" : "MOUNT PERRY",
				"ItemDateTimeUTM" : "20240829205756",
				"ItemDateTimeLocal_ISO" : "2024-08-30T06:57:56+10:00",
				"PublishDateLocal_ISO" : "2024-08-30T23:46:08+10:00",
				"ItemExpiryDateTimeLocal_ISO" : "2024-08-31T06:57:56+10:00"
			}
		},
		{
			"type" : "Feature",
			"geometry" : {
				"type" : "Point",
				"coordinates" : [ 151.82458, -26.96245 ]
			},
			"properties" : {
				"OBJECTID" : "72460",
				"UniqueID" : "QF3-24-104806",
				"WarningTitle" : "Information - COOYAR",
				"WarningLevel" : "Information",
				"CallToAction" : "There is a vegetation fire at this location. Smoke may affect residents and motorists in the area. Residents should close their doors and windows and keep medication close by if suffering from a respiratory condition. Motorists should use caution and drive to conditions. If you believe your property is under threat, you should call Triple Zero (000) immediately.",
				"WarningText" : "There is a vegetation fire at this location. Smoke may affect residents and motorists in the area. Residents should close their doors and windows and keep medication close by if suffering from a respiratory condition. Motorists should use caution and drive to conditions. If you believe your property is under threat, you should call Triple Zero (000) immediately.",
				"Header" : "There is a vegetation fire at this location. Smoke may affect residents and motorists in the area. Residents should close their doors and windows and keep medication close by if suffering from a respiratory condition. Motorists should use caution and drive to conditions. If you believe your property is under threat, you should call Triple Zero (000) immediately.",
				"WarningLevelSort" : "100",
				"WarningArea" : "COOYAR",
				"CurrentStatus" : "Patrolled",
				"Location" : "New England Hwy & Old Cooyar Yarraman Rd",
				"Jurisdiction" : "3 South Western Region",
				"Latitude" : -26.96245,
				"Longitude" : 151.82458,
				"VehiclesAssigned" : "0",
				"VehiclesOnRoute" : "0",
				"VehiclesOnScene" : "0",
				"GroupedType" : "FIRE VEGETATION",
				"Locality" : "COOYAR",
				"ItemDateTimeUTM" : "20240829211201",
				"ItemDateTimeLocal_ISO" : "2024-08-30T07:12:01+10:00",
				"PublishDateLocal_ISO" : "2024-08-30T23:46:08+10:00",
				"ItemExpiryDateTimeLocal_ISO" : "2024-08-31T07:12:01+10:00"
			}
		},
		{
			"type" : "Feature",
			"geometry" : {
				"type" : "Point",
				"coordinates" : [ 151.720433, -26.551838 ]
			},
			"properties" : {
				"OBJECTID" : "72471",
				"UniqueID" : "QF4-24-104831",
				"WarningTitle" : "Information - INVERLAW",
				"WarningLevel" : "Information",
				"CallToAction" : "There is a vegetation fire at this location. Smoke may affect residents and motorists in the area. Residents should close their doors and windows and keep medication close by if suffering from a respiratory condition. Motorists should use caution and drive to conditions. If you believe your property is under threat, you should call Triple Zero (000) immediately.",
				"WarningText" : "There is a vegetation fire at this location. Smoke may affect residents and motorists in the area. Residents should close their doors and windows and keep medication close by if suffering from a respiratory condition. Motorists should use caution and drive to conditions. If you believe your property is under threat, you should call Triple Zero (000) immediately.",
				"Header" : "There is a vegetation fire at this location. Smoke may affect residents and motorists in the area. Residents should close their doors and windows and keep medication close by if suffering from a respiratory condition. Motorists should use caution and drive to conditions. If you believe your property is under threat, you should call Triple Zero (000) immediately.",
				"WarningLevelSort" : "100",
				"WarningArea" : "INVERLAW",
				"CurrentStatus" : "Patrolled",
				"Location" : "Minmore Rd",
				"Jurisdiction" : "4 North Coast Region",
				"Latitude" : -26.551838,
				"Longitude" : 151.720433,
				"VehiclesAssigned" : "0",
				"VehiclesOnRoute" : "0",
				"VehiclesOnScene" : "0",
				"GroupedType" : "FIRE VEGETATION",
				"Locality" : "INVERLAW",
				"ItemDateTimeUTM" : "20240829213237",
				"ItemDateTimeLocal_ISO" : "2024-08-30T07:32:37+10:00",
				"PublishDateLocal_ISO" : "2024-08-30T23:46:08+10:00",
				"ItemExpiryDateTimeLocal_ISO" : "2024-08-31T07:32:37+10:00"
			}
		},
		{
			"type" : "Feature",
			"geometry" : {
				"type" : "Point",
				"coordinates" : [ 149.16438, -21.068076 ]
			},
			"properties" : {
				"OBJECTID" : "72481",
				"UniqueID" : "QF2-24-104856",
				"WarningTitle" : "Information - RURAL VIEW",
				"WarningLevel" : "Information",
				"CallToAction" : "There is a vegetation fire at this location. Smoke may affect residents and motorists in the area. Residents should close their doors and windows and keep medication close by if suffering from a respiratory condition. Motorists should use caution and drive to conditions. If you believe your property is under threat, you should call Triple Zero (000) immediately.",
				"WarningText" : "There is a vegetation fire at this location. Smoke may affect residents and motorists in the area. Residents should close their doors and windows and keep medication close by if suffering from a respiratory condition. Motorists should use caution and drive to conditions. If you believe your property is under threat, you should call Triple Zero (000) immediately.",
				"Header" : "There is a vegetation fire at this location. Smoke may affect residents and motorists in the area. Residents should close their doors and windows and keep medication close by if suffering from a respiratory condition. Motorists should use caution and drive to conditions. If you believe your property is under threat, you should call Triple Zero (000) immediately.",
				"WarningLevelSort" : "100",
				"WarningArea" : "RURAL VIEW",
				"CurrentStatus" : "Patrolled",
				"Location" : "Rosewood Dr",
				"Jurisdiction" : "2 Central Region",
				"Latitude" : -21.068076,
				"Longitude" : 149.16438,
				"VehiclesAssigned" : "0",
				"VehiclesOnRoute" : "0",
				"VehiclesOnScene" : "0",
				"GroupedType" : "FIRE VEGETATION",
				"Locality" : "RURAL VIEW",
				"ItemDateTimeUTM" : "20240829220557",
				"ItemDateTimeLocal_ISO" : "2024-08-30T08:05:57+10:00",
				"PublishDateLocal_ISO" : "2024-08-30T23:46:08+10:00",
				"ItemExpiryDateTimeLocal_ISO" : "2024-08-31T08:05:57+10:00"
			}
		},
		{
			"type" : "Feature",
			"geometry" : {
				"type" : "Point",
				"coordinates" : [ 152.238545, -28.124416 ]
			},
			"properties" : {
				"OBJECTID" : "72490",
				"UniqueID" : "QF3-24-089256",
				"WarningTitle" : "Information - UPPER FREESTONE",
				"WarningLevel" : "Information",
				"CallToAction" : "There is a vegetation fire at this location. Smoke may affect residents and motorists in the area. Residents should close their doors and windows and keep medication close by if suffering from a respiratory condition. Motorists should use caution and drive to conditions. If you believe your property is under threat, you should call Triple Zero (000) immediately.",
				"WarningText" : "There is a vegetation fire at this location. Smoke may affect residents and motorists in the area. Residents should close their doors and windows and keep medication close by if suffering from a respiratory condition. Motorists should use caution and drive to conditions. If you believe your property is under threat, you should call Triple Zero (000) immediately.",
				"Header" : "There is a vegetation fire at this location. Smoke may affect residents and motorists in the area. Residents should close their doors and windows and keep medication close by if suffering from a respiratory condition. Motorists should use caution and drive to conditions. If you believe your property is under threat, you should call Triple Zero (000) immediately.",
				"WarningLevelSort" : "100",
				"WarningArea" : "UPPER FREESTONE",
				"CurrentStatus" : "Patrolled",
				"Location" : "Mcmasters Rd",
				"Jurisdiction" : "3 South Western Region",
				"Latitude" : -28.124416,
				"Longitude" : 152.238545,
				"VehiclesAssigned" : "0",
				"VehiclesOnRoute" : "0",
				"VehiclesOnScene" : "0",
				"GroupedType" : "FIRE VEGETATION",
				"Locality" : "UPPER FREESTONE",
				"ItemDateTimeUTM" : "20240802163226",
				"ItemDateTimeLocal_ISO" : "2024-08-03T02:32:26+10:00",
				"PublishDateLocal_ISO" : "2024-08-30T23:46:08+10:00",
				"ItemExpiryDateTimeLocal_ISO" : "2024-08-04T02:32:26+10:00"
			}
		},
		{
			"type" : "Feature",
			"geometry" : {
				"type" : "Point",
				"coordinates" : [ 145.362712, -16.799976 ]
			},
			"properties" : {
				"OBJECTID" : "72520",
				"UniqueID" : "QF7-24-104935",
				"WarningTitle" : "Information - SOUTHEDGE",
				"WarningLevel" : "Information",
				"CallToAction" : "There is a vegetation fire at this location. Smoke may affect residents and motorists in the area. Residents should close their doors and windows and keep medication close by if suffering from a respiratory condition. Motorists should use caution and drive to conditions. If you believe your property is under threat, you should call Triple Zero (000) immediately.",
				"WarningText" : "There is a vegetation fire at this location. Smoke may affect residents and motorists in the area. Residents should close their doors and windows and keep medication close by if suffering from a respiratory condition. Motorists should use caution and drive to conditions. If you believe your property is under threat, you should call Triple Zero (000) immediately.",
				"Header" : "There is a vegetation fire at this location. Smoke may affect residents and motorists in the area. Residents should close their doors and windows and keep medication close by if suffering from a respiratory condition. Motorists should use caution and drive to conditions. If you believe your property is under threat, you should call Triple Zero (000) immediately.",
				"WarningLevelSort" : "100",
				"WarningArea" : "SOUTHEDGE",
				"CurrentStatus" : "Patrolled",
				"Location" : "Mulligan Hwy",
				"Jurisdiction" : "7 Far Northern Region",
				"Latitude" : -16.799976,
				"Longitude" : 145.362712,
				"VehiclesAssigned" : "0",
				"VehiclesOnRoute" : "0",
				"VehiclesOnScene" : "0",
				"GroupedType" : "FIRE VEGETATION",
				"Locality" : "SOUTHEDGE",
				"ItemDateTimeUTM" : "20240829235546",
				"ItemDateTimeLocal_ISO" : "2024-08-30T09:55:46+10:00",
				"PublishDateLocal_ISO" : "2024-08-30T23:46:08+10:00",
				"ItemExpiryDateTimeLocal_ISO" : "2024-08-31T09:55:46+10:00"
			}
		},
		{
			"type" : "Feature",
			"geometry" : {
				"type" : "Point",
				"coordinates" : [ 152.719161, -27.616315 ]
			},
			"properties" : {
				"OBJECTID" : "72528",
				"UniqueID" : "QF6-24-104947",
				"WarningTitle" : "Information - WULKURAKA",
				"WarningLevel" : "Information",
				"CallToAction" : "There is a vegetation fire at this location. Smoke may affect residents and motorists in the area. Residents should close their doors and windows and keep medication close by if suffering from a respiratory condition. Motorists should use caution and drive to conditions. If you believe your property is under threat, you should call Triple Zero (000) immediately.",
				"WarningText" : "There is a vegetation fire at this location. Smoke may affect residents and motorists in the area. Residents should close their doors and windows and keep medication close by if suffering from a respiratory condition. Motorists should use caution and drive to conditions. If you believe your property is under threat, you should call Triple Zero (000) immediately.",
				"Header" : "There is a vegetation fire at this location. Smoke may affect residents and motorists in the area. Residents should close their doors and windows and keep medication close by if suffering from a respiratory condition. Motorists should use caution and drive to conditions. If you believe your property is under threat, you should call Triple Zero (000) immediately.",
				"WarningLevelSort" : "100",
				"WarningArea" : "WULKURAKA",
				"CurrentStatus" : "Contained",
				"Location" : "CHALK ST & BEIRNE ST",
				"Jurisdiction" : "6 South Eastern Region",
				"Latitude" : -27.616315,
				"Longitude" : 152.719161,
				"VehiclesAssigned" : "0",
				"VehiclesOnRoute" : "1",
				"VehiclesOnScene" : "3",
				"GroupedType" : "FIRE VEGETATION",
				"Locality" : "WULKURAKA",
				"ItemDateTimeUTM" : "20240830003920",
				"ItemDateTimeLocal_ISO" : "2024-08-30T10:39:20+10:00",
				"PublishDateLocal_ISO" : "2024-08-30T23:46:08+10:00",
				"ItemExpiryDateTimeLocal_ISO" : "2024-08-31T10:39:20+10:00"
			}
		},
		{
			"type" : "Feature",
			"geometry" : {
				"type" : "Point",
				"coordinates" : [ 150.395663, -23.47258 ]
			},
			"properties" : {
				"OBJECTID" : "72562",
				"UniqueID" : "QF2-24-105000",
				"WarningTitle" : "Information - KABRA",
				"WarningLevel" : "Information",
				"CallToAction" : "There is a vegetation fire at this location. Smoke may affect residents and motorists in the area. Residents should close their doors and windows and keep medication close by if suffering from a respiratory condition. Motorists should use caution and drive to conditions. If you believe your property is under threat, you should call Triple Zero (000) immediately.",
				"WarningText" : "There is a vegetation fire at this location. Smoke may affect residents and motorists in the area. Residents should close their doors and windows and keep medication close by if suffering from a respiratory condition. Motorists should use caution and drive to conditions. If you believe your property is under threat, you should call Triple Zero (000) immediately.",
				"Header" : "There is a vegetation fire at this location. Smoke may affect residents and motorists in the area. Residents should close their doors and windows and keep medication close by if suffering from a respiratory condition. Motorists should use caution and drive to conditions. If you believe your property is under threat, you should call Triple Zero (000) immediately.",
				"WarningLevelSort" : "100",
				"WarningArea" : "KABRA",
				"CurrentStatus" : "Going",
				"Location" : "NEERKOL ST",
				"Jurisdiction" : "2 Central Region",
				"Latitude" : -23.47258,
				"Longitude" : 150.395663,
				"VehiclesAssigned" : "1",
				"VehiclesOnRoute" : "0",
				"VehiclesOnScene" : "0",
				"GroupedType" : "FIRE VEGETATION",
				"Locality" : "KABRA",
				"ItemDateTimeUTM" : "20240830032505",
				"ItemDateTimeLocal_ISO" : "2024-08-30T13:25:05+10:00",
				"PublishDateLocal_ISO" : "2024-08-30T23:46:08+10:00",
				"ItemExpiryDateTimeLocal_ISO" : "2024-08-31T13:25:05+10:00"
			}
		}
	]
}